{"name":"grunt-cson","tagline":"Grunt CSON plugin","body":"# Grunt CSON plugin [![Build Status](https://travis-ci.org/kevinsawicki/grunt-cson.png)](https://travis-ci.org/kevinsawicki/grunt-cson)\r\n\r\n[Grunt](http://gruntjs.com) plugin to compile CSON files to JSON.\r\n\r\n## Installing\r\n\r\n```sh\r\nnpm install grunt-cson\r\n```\r\n\r\n## Building\r\n  * Clone the repository\r\n  * Run `npm install`\r\n  * Run `grunt` to compile the CoffeeScript code\r\n  * Run `grunt test` to run the specs\r\n  \r\n## Configuring\r\n\r\nAdd the following to your `Gruntfile.coffee`:\r\n\r\n```coffeescript\r\ngrunt.initConfig\r\n  cson:\r\n    glob_to_multiple:\r\n      expand: true\r\n      src: ['src/**/*.cson' ]\r\n      dest: 'lib'\r\n      ext: '.json'\r\n\r\ngrunt.loadNpmTasks('grunt-cson')\r\n```\r\n\r\nThen simply run `grunt cson` to compile all the `.cson` files under `src/`\r\nto `.json` files under `lib/`.\r\n\r\n### Options\r\n\r\nThe following are supported as options to the task configuration.\r\n\r\n```coffeescript\r\ncson:\r\n  options:\r\n    rootObject: true | false\r\n```\r\n\r\n#### rootObject\r\n\r\nSetting this to `true` will verify that each file parsed contains a single\r\nroot object (such as in `package.json`). This option defaults to `false`.\r\n","google":"","note":"Don't delete this file! It's used internally to help with page regeneration."}